[
  {
    "ContainingType": "PagueVeloz.Api.Controllers.AccountController",
    "Method": "Update",
    "RelativePath": "api/Account/AtualizarConta/{accountId}",
    "HttpMethod": "PUT",
    "IsController": true,
    "Order": 0,
    "Parameters": [
      {
        "Name": "AccountNumber",
        "Type": "System.String",
        "IsRequired": false
      },
      {
        "Name": "dto",
        "Type": "PagueVeloz.Application.DTOs.AccountUpdateDto",
        "IsRequired": true
      },
      {
        "Name": "accountId",
        "Type": "",
        "IsRequired": true
      }
    ],
    "ReturnTypes": []
  },
  {
    "ContainingType": "PagueVeloz.Api.Controllers.AccountController",
    "Method": "GetById",
    "RelativePath": "api/Account/BuscarConta/{AccountNumber}",
    "HttpMethod": "GET",
    "IsController": true,
    "Order": 0,
    "Parameters": [
      {
        "Name": "AccountNumber",
        "Type": "System.String",
        "IsRequired": true
      }
    ],
    "ReturnTypes": []
  },
  {
    "ContainingType": "PagueVeloz.Api.Controllers.AccountController",
    "Method": "CriarConta",
    "RelativePath": "api/Account/CriarConta",
    "HttpMethod": "POST",
    "IsController": true,
    "Order": 0,
    "Parameters": [
      {
        "Name": "dto",
        "Type": "PagueVeloz.Api.DTOs.AccountCreateDto",
        "IsRequired": true
      }
    ],
    "ReturnTypes": []
  }
]